mcp_translator/database.py
mcp_translator/server.py
mcp_translator/test_server.py
mcp_translator/text_splitter.py
mcp_translator-0.1.6.dist-info/METADATA
mcp_translator-0.1.6.dist-info/WHEEL
mcp_translator-0.1.6.dist-info/entry_points.txt
mcp_translator-0.1.6.dist-info/top_level.txt
mcp_translator-0.1.6.dist-info/RECORD
