Metadata-Version: 2.4
Name: mcp-translator
Version: 0.1.6
Summary: An MCP server for translating long-form text in chunks.
Author-email: Jiayao Yu <jiayao.yu@gmail.com>
Project-URL: Homepage, https://github.com/jiayao/mcp-translator
Project-URL: Bug Tracker, https://github.com/jiayao/mcp-translator/issues
Classifier: Programming Language :: Python :: 3
Classifier: License :: OSI Approved :: MIT License
Classifier: Operating System :: OS Independent
Requires-Python: >=3.8
Requires-Dist: mcp[cli]>=1.7.1
Requires-Dist: click
Requires-Dist: google-genai
Requires-Dist: mammoth
